[{"name":"start_processing.action_controller","payload":{"controller":"HomeController","action":"index","params":{"controller":"home","action":"index"},"format":"html","method":"GET","path":"/"},"time":"2013-06-07T08:10:08-04:00","transaction_id":"12a0b36f94da87748dc9","end":"2013-06-07T08:10:08-04:00","duration":0.002},{"name":"!render_template.action_view","payload":{"virtual_path":"home/index"},"time":"2013-06-07T08:10:08-04:00","transaction_id":"12a0b36f94da87748dc9","end":"2013-06-07T08:10:08-04:00","duration":0.093},{"name":"render_template.action_view","payload":{"identifier":"/Users/Shefali/Documents/wdi3/projects/gallery/app/views/home/index.html.haml","layout":"layouts/application"},"time":"2013-06-07T08:10:08-04:00","transaction_id":"12a0b36f94da87748dc9","end":"2013-06-07T08:10:08-04:00","duration":0.132},{"name":"!render_template.action_view","payload":{"virtual_path":"layouts/_nav"},"time":"2013-06-07T08:10:08-04:00","transaction_id":"12a0b36f94da87748dc9","end":"2013-06-07T08:10:08-04:00","duration":0.273},{"name":"render_partial.action_view","payload":{"identifier":"/Users/Shefali/Documents/wdi3/projects/gallery/app/views/layouts/_nav.html.erb"},"time":"2013-06-07T08:10:08-04:00","transaction_id":"12a0b36f94da87748dc9","end":"2013-06-07T08:10:08-04:00","duration":0.325},{"name":"!render_template.action_view","payload":{"virtual_path":"layouts/_footer"},"time":"2013-06-07T08:10:08-04:00","transaction_id":"12a0b36f94da87748dc9","end":"2013-06-07T08:10:08-04:00","duration":0.031},{"name":"render_partial.action_view","payload":{"identifier":"/Users/Shefali/Documents/wdi3/projects/gallery/app/views/layouts/_footer.html.erb"},"time":"2013-06-07T08:10:08-04:00","transaction_id":"12a0b36f94da87748dc9","end":"2013-06-07T08:10:08-04:00","duration":0.048},{"name":"!render_template.action_view","payload":{"virtual_path":"layouts/application"},"time":"2013-06-07T08:10:08-04:00","transaction_id":"12a0b36f94da87748dc9","end":"2013-06-07T08:10:08-04:00","duration":71.726},{"name":"process_action.action_controller","payload":{"controller":"HomeController","action":"index","params":{"controller":"home","action":"index"},"format":"html","method":"GET","path":"/","status":200,"view_runtime":73.237,"db_runtime":0},"time":"2013-06-07T08:10:08-04:00","transaction_id":"12a0b36f94da87748dc9","end":"2013-06-07T08:10:08-04:00","duration":73.494}]