[{"name":"start_processing.action_controller","payload":{"controller":"HomeController","action":"index","params":{"controller":"home","action":"index"},"format":"html","method":"GET","path":"/"},"time":"2013-06-07T12:06:49-04:00","transaction_id":"da08425e84cbf3ab92f2","end":"2013-06-07T12:06:49-04:00","duration":0.001},{"name":"!render_template.action_view","payload":{"virtual_path":"home/index"},"time":"2013-06-07T12:06:49-04:00","transaction_id":"da08425e84cbf3ab92f2","end":"2013-06-07T12:06:49-04:00","duration":0.082},{"name":"render_template.action_view","payload":{"identifier":"/Users/Shefali/Documents/wdi3/projects/gallery/app/views/home/index.html.haml","layout":"layouts/application"},"time":"2013-06-07T12:06:49-04:00","transaction_id":"da08425e84cbf3ab92f2","end":"2013-06-07T12:06:49-04:00","duration":0.11900000000000001},{"name":"!render_template.action_view","payload":{"virtual_path":"layouts/_nav"},"time":"2013-06-07T12:06:49-04:00","transaction_id":"da08425e84cbf3ab92f2","end":"2013-06-07T12:06:49-04:00","duration":0.424},{"name":"render_partial.action_view","payload":{"identifier":"/Users/Shefali/Documents/wdi3/projects/gallery/app/views/layouts/_nav.html.erb"},"time":"2013-06-07T12:06:49-04:00","transaction_id":"da08425e84cbf3ab92f2","end":"2013-06-07T12:06:49-04:00","duration":0.46900000000000003},{"name":"!render_template.action_view","payload":{"virtual_path":"layouts/_footer"},"time":"2013-06-07T12:06:49-04:00","transaction_id":"da08425e84cbf3ab92f2","end":"2013-06-07T12:06:49-04:00","duration":0.054},{"name":"render_partial.action_view","payload":{"identifier":"/Users/Shefali/Documents/wdi3/projects/gallery/app/views/layouts/_footer.html.erb"},"time":"2013-06-07T12:06:49-04:00","transaction_id":"da08425e84cbf3ab92f2","end":"2013-06-07T12:06:49-04:00","duration":0.06999999999999999},{"name":"!render_template.action_view","payload":{"virtual_path":"layouts/application"},"time":"2013-06-07T12:06:49-04:00","transaction_id":"da08425e84cbf3ab92f2","end":"2013-06-07T12:06:49-04:00","duration":73.084},{"name":"process_action.action_controller","payload":{"controller":"HomeController","action":"index","params":{"controller":"home","action":"index"},"format":"html","method":"GET","path":"/","status":200,"view_runtime":74.36,"db_runtime":0},"time":"2013-06-07T12:06:49-04:00","transaction_id":"da08425e84cbf3ab92f2","end":"2013-06-07T12:06:49-04:00","duration":74.625}]